formula_validation/Adduct.py
formula_validation/Element.py
formula_validation/Formula.py
formula_validation/FormulaPrediction.py
formula_validation/IncorrectAdduct.py
formula_validation/IncorrectFormula.py
formula_validation/NotFoundElement.py
formula_validation/__init__.py
formula_validation-1.0.4.dist-info/LICENSE
formula_validation-1.0.4.dist-info/METADATA
formula_validation-1.0.4.dist-info/WHEEL
formula_validation-1.0.4.dist-info/RECORD
