Metadata-Version: 2.1
Name: formula_validation
Version: 1.0.4
Summary: Package to represent formulas with adducts and process ms data from it. 
Home-page: https://github.com/Wang-Bioinformatics-Lab/formula_validation
License: GPL-3.0-only
Keywords: ms,chemistry
Author: Alberto Gil de la Fuente
Author-email: alberto.gilf@gmail.com
Maintainer: Alberto Gil de la Fuente
Maintainer-email: alberto.gilf@gmail.com
Requires-Python: >3.8
Classifier: Development Status :: 3 - Alpha
Classifier: Intended Audience :: Science/Research
Classifier: License :: OSI Approved :: GNU General Public License v3 (GPLv3)
Classifier: Operating System :: POSIX :: Linux
Classifier: Programming Language :: Python :: 3
Classifier: Programming Language :: Python :: 3.9
Classifier: Programming Language :: Python :: 3.10
Classifier: Programming Language :: Python :: 3.11
Classifier: Programming Language :: Python :: 3.12
Requires-Dist: rdkit (>2023.9.5)
Requires-Dist: urllib3 (>=1.0,<2.0)
Project-URL: Repository, https://github.com/Wang-Bioinformatics-Lab/formula_validation
